fuo_ytmusic/__init__.py
fuo_ytmusic/consts.py
fuo_ytmusic/helpers.py
fuo_ytmusic/models.py
fuo_ytmusic/page_explore_qml.py
fuo_ytmusic/page_more.py
fuo_ytmusic/provider.py
fuo_ytmusic/provider_ui.py
fuo_ytmusic/qt_compat.py
fuo_ytmusic/service.py
fuo_ytmusic/timeparse.py
fuo_ytmusic/assets/icon.svg
fuo_ytmusic/qml/page_explore.qml
fuo_ytmusic/qml/uploader.qml
fuo_ytmusic/qml/dummydata/explore_backend.qml
fuo_ytmusic-0.4.14.dist-info/licenses/LICENSE.txt
fuo_ytmusic-0.4.14.dist-info/METADATA
fuo_ytmusic-0.4.14.dist-info/WHEEL
fuo_ytmusic-0.4.14.dist-info/entry_points.txt
fuo_ytmusic-0.4.14.dist-info/top_level.txt
fuo_ytmusic-0.4.14.dist-info/RECORD
