Metadata-Version: 2.4
Name: fuo-ytmusic
Version: 0.4.14
Summary: feeluown Youtube Music plugin
Author-email: Bruce Zhang <zttt183525594@gmail.com>
License:                     GNU GENERAL PUBLIC LICENSE
Project-URL: Homepage, https://github.com/feeluown/feeluown-ytmusic
Project-URL: Repository, https://github.com/feeluown/feeluown-ytmusic
Keywords: feeluown,ytmusic,youtube
Requires-Python: <4.0,>=3.8
License-File: LICENSE.txt
Requires-Dist: feeluown>=3.8.12
Requires-Dist: ytmusicapi
Requires-Dist: pydantic<3.0,>=2.0
Requires-Dist: cachetools
Requires-Dist: yt-dlp
Dynamic: license-file
